readerDAS/__init__.py
readerDAS/classes.py
readerDAS/errors.py
readerDAS/main.py
readerDAS/sottocampionamento.py
readerDAS/utils.py
readerDAS/versioning.py
readerdas-1.1.5.dist-info/METADATA
readerdas-1.1.5.dist-info/WHEEL
readerdas-1.1.5.dist-info/RECORD
