Metadata-Version: 2.3
Name: readerDAS
Version: 1.1.5
Summary: Package to load files saved by Cohaerentia DAS Interrogator.
Author: Marco Brunero
Author-email: marco.brunero@cohaerentia.com
Requires-Python: >=3.12,<4.0
Classifier: Programming Language :: Python :: 3
Classifier: Programming Language :: Python :: 3.12
Classifier: Programming Language :: Python :: 3.13
Requires-Dist: h5py (>=3.12.1,<4.0.0)
Requires-Dist: numpy (>=2.1.2,<3.0.0)
Requires-Dist: packaging (>=25.0,<26.0)
Requires-Dist: plotly (>=6.2.0,<7.0.0)
Requires-Dist: scipy (>=1.15.2,<2.0.0)
Requires-Dist: tqdm (>=4.67.0,<5.0.0)
Requires-Dist: tzlocal (>=5.2,<6.0)
